{
	"backtrace" : 2,
	"backtraceGraph" : 
	{
		"commands" : 
		[
			"add_custom_target",
			"doxygen_add_docs"
		],
		"files" : 
		[
			"/home/mahdi/Downloads/clion-2024.1.1/bin/cmake/linux/x64/share/cmake-3.28/Modules/FindDoxygen.cmake",
			"doc/CMakeLists.txt"
		],
		"nodes" : 
		[
			{
				"file" : 1
			},
			{
				"command" : 1,
				"file" : 1,
				"line" : 28,
				"parent" : 0
			},
			{
				"command" : 0,
				"file" : 0,
				"line" : 1208,
				"parent" : 1
			}
		]
	},
	"id" : "doc::@c2466c91de71b9c692d9",
	"name" : "doc",
	"paths" : 
	{
		"build" : "doc",
		"source" : "doc"
	},
	"sourceGroups" : 
	[
		{
			"name" : "",
			"sourceIndexes" : 
			[
				0
			]
		},
		{
			"name" : "CMake Rules",
			"sourceIndexes" : 
			[
				1
			]
		}
	],
	"sources" : 
	[
		{
			"backtrace" : 2,
			"isGenerated" : true,
			"path" : "cmake-build-debug/doc/CMakeFiles/doc",
			"sourceGroupIndex" : 0
		},
		{
			"backtrace" : 0,
			"isGenerated" : true,
			"path" : "cmake-build-debug/doc/CMakeFiles/doc.rule",
			"sourceGroupIndex" : 1
		}
	],
	"type" : "UTILITY"
}
